mcp_server.py
semantic_retrieval_data-0.1.0.dist-info/METADATA
semantic_retrieval_data-0.1.0.dist-info/WHEEL
semantic_retrieval_data-0.1.0.dist-info/entry_points.txt
semantic_retrieval_data-0.1.0.dist-info/top_level.txt
semantic_retrieval_data-0.1.0.dist-info/RECORD
