Metadata-Version: 2.4
Name: semantic-retrieval-data
Version: 0.1.0
Requires-Dist: mcp
Requires-Dist: httpx
Requires-Dist: pyyaml
